[{
        "question": " \n(function()\n{\nreturn \ntypeof \narguments;\n})();} ",

        "options": ["Object", "Array", "argument", "undefined"],
        "answer": "Object"
    },
    {
        "question": "Inside which HTML element do we put the JavaScript",
        "options": ["<javscript>", "<script>", "<sripting>", "<js.script>"],
        "answer": "<script>"
    },
    {
        "question": "Javscript is case sensitive Language",
        "options": ["True", "False"],
        "answer": "True"
    },
    {
        "question": "Which method combines two strings and returns a new string",
        "options": ["append()", "concat()", "attach()", "fetch()"],
        "answer": "concat()"
    }
]